[
	{
		"c32": {},
		"c64": {},
		"type": "ctm",
		"folder": "ctm/bookshelf",
		"textures": [
			"0.png","1.png","2.png","3.png"
		]
	},
	{
		"c32": {},
		"c64": {},
		"type": "ctm",
		"folder": "ctm/glass/black_stained_glass",
		"textures": [
			"0.png","1.png","2.png","3.png","4.png","5.png","6.png","7.png","8.png","9.png","10.png","11.png","12.png","13.png","14.png","15.png","16.png","1.png7","18.png","19.png","20.png","21.png","22.png","23.png","24.png","25.png","26.png","27.png","28.png","29.png","30.png","31.png","32.png","3.png3","34.png","35.png","36.png","37.png","38.png","39.png","40.png","41.png","42.png","43.png","44.png","45.png","46.png"
		]
	},
	{
		"c32": {},
		"c64": {},
		"type": "ctm",
		"folder": "ctm/glass/blue_stained_glass",
		"textures": [
			"0.png","1.png","2.png","3.png","4.png","5.png","6.png","7.png","8.png","9.png","10.png","11.png","12.png","13.png","14.png","15.png","16.png","1.png7","18.png","19.png","20.png","21.png","22.png","23.png","24.png","25.png","26.png","27.png","28.png","29.png","30.png","31.png","32.png","3.png3","34.png","35.png","36.png","37.png","38.png","39.png","40.png","41.png","42.png","43.png","44.png","45.png","46.png"
		]
	},
	{
		"c32": {},
		"c64": {},
		"type": "ctm",
		"folder": "ctm/glass/brown_stained_glass",
		"textures": [
			"0.png","1.png","2.png","3.png","4.png","5.png","6.png","7.png","8.png","9.png","10.png","11.png","12.png","13.png","14.png","15.png","16.png","1.png7","18.png","19.png","20.png","21.png","22.png","23.png","24.png","25.png","26.png","27.png","28.png","29.png","30.png","31.png","32.png","3.png3","34.png","35.png","36.png","37.png","38.png","39.png","40.png","41.png","42.png","43.png","44.png","45.png","46.png"
		]
	},
	{
		"c32": {},
		"c64": {},
		"type": "ctm",
		"folder": "ctm/glass/cyan_stained_glass",
		"textures": [
			"0.png","1.png","2.png","3.png","4.png","5.png","6.png","7.png","8.png","9.png","10.png","11.png","12.png","13.png","14.png","15.png","16.png","1.png7","18.png","19.png","20.png","21.png","22.png","23.png","24.png","25.png","26.png","27.png","28.png","29.png","30.png","31.png","32.png","3.png3","34.png","35.png","36.png","37.png","38.png","39.png","40.png","41.png","42.png","43.png","44.png","45.png","46.png"
		]
	},
	{
		"c32": {},
		"c64": {},
		"type": "ctm",
		"folder": "ctm/glass/glass",
		"textures": [
			"0.png","1.png","2.png","3.png","4.png","5.png","6.png","7.png","8.png","9.png","10.png","11.png","12.png","13.png","14.png","15.png","16.png","1.png7","18.png","19.png","20.png","21.png","22.png","23.png","24.png","25.png","26.png","27.png","28.png","29.png","30.png","31.png","32.png","3.png3","34.png","35.png","36.png","37.png","38.png","39.png","40.png","41.png","42.png","43.png","44.png","45.png","46.png"
		]
	},
	{
		"c32": {},
		"c64": {},
		"type": "ctm",
		"folder": "ctm/glass/gray_stained_glass",
		"textures": [
			"0.png","1.png","2.png","3.png","4.png","5.png","6.png","7.png","8.png","9.png","10.png","11.png","12.png","13.png","14.png","15.png","16.png","1.png7","18.png","19.png","20.png","21.png","22.png","23.png","24.png","25.png","26.png","27.png","28.png","29.png","30.png","31.png","32.png","3.png3","34.png","35.png","36.png","37.png","38.png","39.png","40.png","41.png","42.png","43.png","44.png","45.png","46.png"
		]
	},
	{
		"c32": {},
		"c64": {},
		"type": "ctm",
		"folder": "ctm/glass/green_stained_glass",
		"textures": [
			"0.png","1.png","2.png","3.png","4.png","5.png","6.png","7.png","8.png","9.png","10.png","11.png","12.png","13.png","14.png","15.png","16.png","1.png7","18.png","19.png","20.png","21.png","22.png","23.png","24.png","25.png","26.png","27.png","28.png","29.png","30.png","31.png","32.png","3.png3","34.png","35.png","36.png","37.png","38.png","39.png","40.png","41.png","42.png","43.png","44.png","45.png","46.png"
		]
	},
	{
		"c32": {},
		"c64": {},
		"type": "ctm",
		"folder": "ctm/glass/light_blue_stained_glass",
		"textures": [
			"0.png","1.png","2.png","3.png","4.png","5.png","6.png","7.png","8.png","9.png","10.png","11.png","12.png","13.png","14.png","15.png","16.png","1.png7","18.png","19.png","20.png","21.png","22.png","23.png","24.png","25.png","26.png","27.png","28.png","29.png","30.png","31.png","32.png","3.png3","34.png","35.png","36.png","37.png","38.png","39.png","40.png","41.png","42.png","43.png","44.png","45.png","46.png"
		]
	},
	{
		"c32": {},
		"c64": {},
		"type": "ctm",
		"folder": "ctm/glass/light_gray_stained_glass",
		"textures": [
			"0.png","1.png","2.png","3.png","4.png","5.png","6.png","7.png","8.png","9.png","10.png","11.png","12.png","13.png","14.png","15.png","16.png","1.png7","18.png","19.png","20.png","21.png","22.png","23.png","24.png","25.png","26.png","27.png","28.png","29.png","30.png","31.png","32.png","3.png3","34.png","35.png","36.png","37.png","38.png","39.png","40.png","41.png","42.png","43.png","44.png","45.png","46.png"
		]
	},
	{
		"c32": {},
		"c64": {},
		"type": "ctm",
		"folder": "ctm/glass/lime_stained_glass",
		"textures": [
			"0.png","1.png","2.png","3.png","4.png","5.png","6.png","7.png","8.png","9.png","10.png","11.png","12.png","13.png","14.png","15.png","16.png","1.png7","18.png","19.png","20.png","21.png","22.png","23.png","24.png","25.png","26.png","27.png","28.png","29.png","30.png","31.png","32.png","3.png3","34.png","35.png","36.png","37.png","38.png","39.png","40.png","41.png","42.png","43.png","44.png","45.png","46.png"
		]
	},
	{
		"c32": {},
		"c64": {},
		"type": "ctm",
		"folder": "ctm/glass/magenta_stained_glass",
		"textures": [
			"0.png","1.png","2.png","3.png","4.png","5.png","6.png","7.png","8.png","9.png","10.png","11.png","12.png","13.png","14.png","15.png","16.png","1.png7","18.png","19.png","20.png","21.png","22.png","23.png","24.png","25.png","26.png","27.png","28.png","29.png","30.png","31.png","32.png","3.png3","34.png","35.png","36.png","37.png","38.png","39.png","40.png","41.png","42.png","43.png","44.png","45.png","46.png"
		]
	},
	{
		"c32": {},
		"c64": {},
		"type": "ctm",
		"folder": "ctm/glass/orange_stained_glass",
		"textures": [
			"0.png","1.png","2.png","3.png","4.png","5.png","6.png","7.png","8.png","9.png","10.png","11.png","12.png","13.png","14.png","15.png","16.png","1.png7","18.png","19.png","20.png","21.png","22.png","23.png","24.png","25.png","26.png","27.png","28.png","29.png","30.png","31.png","32.png","3.png3","34.png","35.png","36.png","37.png","38.png","39.png","40.png","41.png","42.png","43.png","44.png","45.png","46.png"
		]
	},
	{
		"c32": {},
		"c64": {},
		"type": "ctm",
		"folder": "ctm/glass/pink_stained_glass",
		"textures": [
			"0.png","1.png","2.png","3.png","4.png","5.png","6.png","7.png","8.png","9.png","10.png","11.png","12.png","13.png","14.png","15.png","16.png","1.png7","18.png","19.png","20.png","21.png","22.png","23.png","24.png","25.png","26.png","27.png","28.png","29.png","30.png","31.png","32.png","3.png3","34.png","35.png","36.png","37.png","38.png","39.png","40.png","41.png","42.png","43.png","44.png","45.png","46.png"
		]
	},
	{
		"c32": {},
		"c64": {},
		"type": "ctm",
		"folder": "ctm/glass/purple_stained_glass",
		"textures": [
			"0.png","1.png","2.png","3.png","4.png","5.png","6.png","7.png","8.png","9.png","10.png","11.png","12.png","13.png","14.png","15.png","16.png","1.png7","18.png","19.png","20.png","21.png","22.png","23.png","24.png","25.png","26.png","27.png","28.png","29.png","30.png","31.png","32.png","3.png3","34.png","35.png","36.png","37.png","38.png","39.png","40.png","41.png","42.png","43.png","44.png","45.png","46.png"
		]
	},
	{
		"c32": {},
		"c64": {},
		"type": "ctm",
		"folder": "ctm/glass/red_stained_glass",
		"textures": [
			"0.png","1.png","2.png","3.png","4.png","5.png","6.png","7.png","8.png","9.png","10.png","11.png","12.png","13.png","14.png","15.png","16.png","1.png7","18.png","19.png","20.png","21.png","22.png","23.png","24.png","25.png","26.png","27.png","28.png","29.png","30.png","31.png","32.png","3.png3","34.png","35.png","36.png","37.png","38.png","39.png","40.png","41.png","42.png","43.png","44.png","45.png","46.png"
		]
	},
	{
		"c32": {},
		"c64": {},
		"type": "ctm",
		"folder": "ctm/glass/white_stained_glass",
		"textures": [
			"0.png","1.png","2.png","3.png","4.png","5.png","6.png","7.png","8.png","9.png","10.png","11.png","12.png","13.png","14.png","15.png","16.png","1.png7","18.png","19.png","20.png","21.png","22.png","23.png","24.png","25.png","26.png","27.png","28.png","29.png","30.png","31.png","32.png","3.png3","34.png","35.png","36.png","37.png","38.png","39.png","40.png","41.png","42.png","43.png","44.png","45.png","46.png"
		]
	},
	{
		"c32": {},
		"c64": {},
		"type": "ctm",
		"folder": "ctm/glass/yellow_stained_glass",
		"textures": [
			"0.png","1.png","2.png","3.png","4.png","5.png","6.png","7.png","8.png","9.png","10.png","11.png","12.png","13.png","14.png","15.png","16.png","1.png7","18.png","19.png","20.png","21.png","22.png","23.png","24.png","25.png","26.png","27.png","28.png","29.png","30.png","31.png","32.png","3.png3","34.png","35.png","36.png","37.png","38.png","39.png","40.png","41.png","42.png","43.png","44.png","45.png","46.png"
		]
	},
	{
		"c32": {},
		"c64": {},
		"type": "ctm",
		"folder": "ctm/glass/gray_stained_glass",
		"textures": [
			"0.png","1.png","2.png","3.png","4.png","5.png","6.png","7.png","8.png","9.png","10.png","11.png","12.png","13.png","14.png","15.png","16.png","1.png7","18.png","19.png","20.png","21.png","22.png","23.png","24.png","25.png","26.png","27.png","28.png","29.png","30.png","31.png","32.png","3.png3","34.png","35.png","36.png","37.png","38.png","39.png","40.png","41.png","42.png","43.png","44.png","45.png","46.png"
		]
	},
	{
		"c32": {},
		"c64": {},
		"type": "ctm",
		"folder": "ctm/red_sandstone",
		"textures": [
			"0.png","1.png","2.png","3.png"
		]
	},
	{
		"c32": {},
		"c64": {},
		"type": "ctm",
		"folder": "ctm/sandstone",
		"textures": [
			"0.png","1.png","2.png","3.png"
		]
	},
	{
		"c32": {},
		"c64": {},
		"type": "texture",
		"folder": "textures",
		"textures": [
			"icons.png"
		]
	}
]